{
    "list": [{
        "no": "1",
        "user_name": "安徽大众4s店",
        "date_reg": "2018-08-07 00:00:00",
        "count_invest": "5",
        "count_frozen": "0",
        "status": "已审核",
        "money_invest": "6890元",
        "money_income": "560元",
        "count_inproject": "3",
        "money_inproject": "3765元"
    }, {
        "no": "2",
        "user_name": "安徽大众4s店",
        "date_reg": "2018-08-07 00:00:00",
        "count_invest": "5",
        "count_frozen": "0",
        "status": "已审核",
        "money_invest": "6890元",
        "money_income": "560元",
        "count_inproject": "3",
        "money_inproject": "3765元"
    },{
        "no": "3",
        "user_name": "安徽大众4s店",
        "date_reg": "2018-08-07 00:00:00",
        "count_frozen": "0",
        "status": "已审核",
        "count_invest": "5",
        "money_invest": "6890元",
        "money_income": "560元",
        "count_inproject": "3",
        "money_inproject": "3765元"
    },{
        "no": "4",
        "user_name": "安徽大众4s店",
        "date_reg": "2018-08-07 00:00:00",
        "count_frozen": "0",
        "status": "已审核",
        "count_invest": "5",
        "money_invest": "6890元",
        "money_income": "560元",
        "count_inproject": "3",
        "money_inproject": "3765元"
    },{
        "no": "5",
        "user_name": "安徽大众4s店",
        "date_reg": "2018-08-07 00:00:00",
        "count_frozen": "0",
        "status": "已审核",
        "count_invest": "5",
        "money_invest": "6890元",
        "money_income": "560元",
        "count_inproject": "3",
        "money_inproject": "3765元"
    },{
        "no": "6",
        "user_name": "安徽大众4s店",
        "date_reg": "2018-08-07 00:00:00",
        "count_frozen": "0",
        "status": "已审核",
        "count_invest": "5",
        "money_invest": "6890元",
        "money_income": "560元",
        "count_inproject": "3",
        "money_inproject": "3765元"
    },{
        "no": "7",
        "user_name": "安徽大众4s店",
        "date_reg": "2018-08-07 00:00:00",
        "count_frozen": "0",
        "status": "已审核",
        "count_invest": "5",
        "money_invest": "6890元",
        "money_income": "560元",
        "count_inproject": "3",
        "money_inproject": "3765元"
    },{
        "no": "8",
        "user_name": "安徽大众4s店",
        "date_reg": "2018-08-07 00:00:00",
        "count_frozen": "0",
        "status": "已审核",
        "count_invest": "5",
        "money_invest": "6890元",
        "money_income": "560元",
        "count_inproject": "3",
        "money_inproject": "3765元"
    },{
        "no": "9",
        "user_name": "安徽大众4s店",
        "date_reg": "2018-08-07 00:00:00",
        "count_frozen": "0",
        "status": "已审核",
        "count_invest": "5",
        "money_invest": "6890元",
        "money_income": "560元",
        "count_inproject": "3",
        "money_inproject": "3765元"
    }]
}
